hangman_46165/hangman_46165.py
hangman_46165-0.1.dist-info/METADATA
hangman_46165-0.1.dist-info/WHEEL
hangman_46165-0.1.dist-info/top_level.txt
hangman_46165-0.1.dist-info/RECORD
